markupflow/__init__.py
markupflow/py.typed
markupflow-0.0.2.dist-info/METADATA
markupflow-0.0.2.dist-info/WHEEL
markupflow-0.0.2.dist-info/licenses/LICENSE
markupflow-0.0.2.dist-info/RECORD
