Metadata-Version: 2.4
Name: markupflow
Version: 0.0.2
Summary: Generate HTML, the Pythonic way
Project-URL: Documentation, https://frankie567.github.io/markupflow/
Project-URL: Source, https://github.com/frankie567/markupflow
Author-email: markupflow <francois@francoisvoron.com>
License-File: LICENSE
Classifier: Programming Language :: Python :: 3 :: Only
Classifier: Programming Language :: Python :: 3.12
Requires-Python: >=3.12
